de2120_barcode_scanner.py
de2120_barcode_scanner-0.0.1.dist-info/LICENSE
de2120_barcode_scanner-0.0.1.dist-info/METADATA
de2120_barcode_scanner-0.0.1.dist-info/WHEEL
de2120_barcode_scanner-0.0.1.dist-info/top_level.txt
de2120_barcode_scanner-0.0.1.dist-info/RECORD
